README.rst
setup.py
simple_nose_selenium/__init__.py
simple_nose_selenium/driver_builder.py
simple_nose_selenium/simple_nose_selenium.py
simple_nose_selenium/test_case.py
simple_nose_selenium/util.py
simple_nose_selenium.egg-info/PKG-INFO
simple_nose_selenium.egg-info/SOURCES.txt
simple_nose_selenium.egg-info/dependency_links.txt
simple_nose_selenium.egg-info/entry_points.txt
simple_nose_selenium.egg-info/requires.txt
simple_nose_selenium.egg-info/top_level.txt
simple_nose_selenium/saucelabs/__init__.py
simple_nose_selenium/saucelabs/saucelabs_client.py
simple_nose_selenium/saucelabs/saucelabs_driver_builder.py