Metadata-Version: 1.1
Name: simple-nose-selenium
Version: 0.2.0
Summary: Run your Selenium TestCase's in chrome, firefox or saucelabs
Home-page: http://github.com/felix-d/simple-nose-selenium
Author: Felix Descoteaux
Author-email: flx.descoteaux@gmail.com
License: Mozilla Public License 2.0 (MPL 2.0)
Keywords: nose selenium webdriver
Platform: UNKNOWN
Classifier: Development Status :: 2 - Pre-Alpha
Classifier: Intended Audience :: Developers
Classifier: License :: OSI Approved :: Mozilla Public License 2.0 (MPL 2.0)
Classifier: Operating System :: POSIX
Classifier: Operating System :: Microsoft :: Windows
Classifier: Operating System :: MacOS :: MacOS X
Classifier: Topic :: Software Development :: Quality Assurance
Classifier: Topic :: Software Development :: Testing
Classifier: Topic :: Utilities
Classifier: Programming Language :: Python
Classifier: Programming Language :: Python :: 3
